{
  "HOST": "https://api.liveforfootball.com"

, "HTTP": {
    "SECURE": true
  } 

, "RETHINKDB": {
    "DATABASE": "production"
  }

, "PROVIDER": {
    "EMAIL": "sendgrid"
  }

, "LOGGING": {
    "TYPE": "papertrail"
  , "FORMAT": "tiny"
  , "STACK": true
  }

, "PAPERTRAIL": {
    "HOST": "logs4.papertrailapp.com"
  , "PORT": 24180
  }

, "FACEBOOK": {
    "ID": "1080273218682225"
  , "SECRET": "efb85c3ecc9eccbcda064a65c53f2036"
  , "SCOPE": "email,user_likes,user_friends"
  }

, "TWITTER": {
    "ID": "5wnn54lBCwxZC93Rojn4FPUWj"
  , "SECRET": "J3y5SNoc3ZCVsLOhrUCMJ09vT4IvNTPAOO0pX6NzAcmgiayuNO"

  , "TOKEN": {
      "TOKEN": "3297881-GHEixgZxEprDvyY9W9U2ej65U9V3ljI9LmZKIB0LE1"
    , "SECRET": "0CDF0M41vhf2Y47YiXysU9pHtVJy7HkRM9jdLEEn766nP"
    }

  }
, "GOOGLE": {
    "ID": "1093341044047-gdmevr2jfn00ichto2rgdnv9b4fspt08.apps.googleusercontent.com"
  , "SECRET": "klpRRpXNkZemy3kRP36pYgjq"
  }  

}
